eadb/__about__.py
eadb/__init__.py
eadb/android_cmd.py
eadb/cli.py
eadb/common_cmd.py
eadb/help_content.py
eadb/ios_cmd.py
eadb/utils.py
Eadb-0.3.2.dist-info/LICENSE
Eadb-0.3.2.dist-info/METADATA
Eadb-0.3.2.dist-info/WHEEL
Eadb-0.3.2.dist-info/entry_points.txt
Eadb-0.3.2.dist-info/top_level.txt
Eadb-0.3.2.dist-info/RECORD
