Metadata-Version: 2.1
Name: Eadb
Version: 0.3.2
Summary: make adb more easy
Home-page: https://github.com/wenshi11019/eadb
Author: DC_ing
Author-email: dc_ing@qq.com
License: MIT
Keywords: Android adb
Platform: UNKNOWN
Classifier: Development Status :: 3 - Alpha
Classifier: Programming Language :: Python :: 3.4
Classifier: Programming Language :: Python :: 3.5
Classifier: Programming Language :: Python :: 3.6
Classifier: Programming Language :: Python :: 3.7
Requires-Python: >=3.0, <4
